job.py
uv_job-0.1.1.dist-info/licenses/LICENSE
uv_job-0.1.1.dist-info/METADATA
uv_job-0.1.1.dist-info/WHEEL
uv_job-0.1.1.dist-info/entry_points.txt
uv_job-0.1.1.dist-info/top_level.txt
uv_job-0.1.1.dist-info/RECORD
