Metadata-Version: 2.4
Name: uv-job
Version: 0.1.1
Summary: Simple task runner for uv
Requires-Python: >=3.9
License-File: LICENSE
Requires-Dist: tomli>=1.2.0; python_version < "3.11"
Dynamic: license-file
